[
  {
    "element_id": "c85008d0df149afae3add14895d2f447",
    "text": "This transmits obsolete IRM 7.25, Exempt Organizations Determination Manual, Business",
    "type": "NarrativeText",
    "metadata": {
      "filename": "zips/irm07-025-006--2019-12-03.pdf",
      "page_number": 1
    }
  },
  {
    "element_id": "c5ceacd1d7364443a46bc39a13c7a24c",
    "text": "This material is obsolete, having undergone a conversion to a Technical Resource Guide. You can ﬁnd the guide at the EO Knowledge Networks SharePoint site.",
    "type": "NarrativeText",
    "metadata": {
      "filename": "zips/irm07-025-006--2019-12-03.pdf",
      "page_number": 1
    }
  },
  {
    "element_id": "e6433af1ab1f412e34139c6fa827f024",
    "text": "This obsoletes IRM 7.25.6 dated June 1, 2001.",
    "type": "NarrativeText",
    "metadata": {
      "filename": "zips/irm07-025-006--2019-12-03.pdf",
      "page_number": 1
    }
  },
  {
    "element_id": "c9df9e6cee1df56fd987d4a59f3bfeb1",
    "text": "Tax Exempt and Government Entities Organizations",
    "type": "NarrativeText",
    "metadata": {
      "filename": "zips/irm07-025-006--2019-12-03.pdf",
      "page_number": 1
    }
  }
]